bloqly.py
bloqly-0.6.dist-info/LICENSE
bloqly-0.6.dist-info/WHEEL
bloqly-0.6.dist-info/METADATA
bloqly-0.6.dist-info/RECORD
