Metadata-Version: 2.1
Name: bloqly
Version: 0.6
Summary: Bloqly API
Home-page: https://bloqly.com
License: UNKNOWN
Author: Bloqly developers
Author-email: team@bloqly.com
Classifier: License :: OSI Approved :: MIT License
Requires-Dist: requests >= 2.21.0
Requires-Dist: pynacl >= 1.3.0
